bindings/__init__.py
bindings/bindings.py
bindings/generated/DataKVP.py
bindings/generated/FBArray.py
bindings/generated/FBBacktest.py
bindings/generated/IndicatorRequest.py
bindings/generated/InputSeries.py
bindings/generated/LogicGraph.py
bindings/generated/Node.py
bindings/generated/NodeKVP.py
bindings/generated/Parameter.py
bindings/generated/ValueGraph.py
bindings/generated/__init__.py
bindings/src/__init__.py
bindings/src/deserialize.py
bindings/src/serialize.py
fftwb/__init__.py
fftwb/twb.cpython-311-x86_64-linux-gnu.so
fftwb-0.1.1.dist-info/METADATA
fftwb-0.1.1.dist-info/WHEEL
fftwb-0.1.1.dist-info/top_level.txt
fftwb-0.1.1.dist-info/RECORD
