Metadata-Version: 2.1
Name: fftwb
Version: 0.1.1
Summary: The bindings for the C++ backtesting engine.
Author: Formula Finance
Author-email: 
Classifier: Programming Language :: Python :: 3
Classifier: License :: OSI Approved :: MIT License
Classifier: Operating System :: OS Independent
Requires-Python: >=3.11
